tablegen/__init__.py
tablegen/cli.py
tablegen/constants.py
tablegen/utils.py
tablegen/handlers/__init__.py
tablegen/handlers/base_handler.py
tablegen/handlers/buck.py
tablegen/handlers/buck_ext.py
tablegen/handlers/pmmcs.py
tablegen/handlers/shik.py
tablegen/handlers/shik_depr.py
tablegen/handlers/sw_3b.py
tablegen/handlers/teter.py
tablegen/handlers/trunc3b.py
lammps_tablegen-0.3.1.dist-info/METADATA
lammps_tablegen-0.3.1.dist-info/WHEEL
lammps_tablegen-0.3.1.dist-info/entry_points.txt
lammps_tablegen-0.3.1.dist-info/licenses/LICENSE
lammps_tablegen-0.3.1.dist-info/RECORD
