Metadata-Version: 2.4
Name: lammps-tablegen
Version: 0.3.1
Summary: Generator for LAMMPS two-body and three-body tabulated potentials.
Project-URL: Homepage, https://github.com/superde1fin/tablegen
Project-URL: Source, https://github.com/superde1fin/tablegen
Project-URL: Issues, https://github.com/superde1fin/tablegen/issues
License: GPL-3.0-only
License-File: LICENSE
Requires-Python: >=3.9
Requires-Dist: matplotlib>=3.9
Requires-Dist: mpmath>=1.3
Requires-Dist: numpy>=1.26
Provides-Extra: dev
Requires-Dist: build>=1.2; extra == 'dev'
Requires-Dist: mypy>=1.10; extra == 'dev'
Requires-Dist: pytest>=8.1; extra == 'dev'
Requires-Dist: ruff>=0.4; extra == 'dev'
Requires-Dist: twine>=5.0; extra == 'dev'
